huawei_hg659/Connector.py
huawei_hg659/__init__.py
huawei_hg659-0.0.4.dist-info/LICENSE.txt
huawei_hg659-0.0.4.dist-info/METADATA
huawei_hg659-0.0.4.dist-info/WHEEL
huawei_hg659-0.0.4.dist-info/top_level.txt
huawei_hg659-0.0.4.dist-info/RECORD
