Metadata-Version: 2.1
Name: huawei-hg659
Version: 0.0.4
Summary: Scraper for Huawei HG659 Router
Home-page: https://github.com/PretentiousPotatoPeeler/huawei-hg659/
Author: Pepijn Compaan
Author-email: pepijncompaan@gmail.com
License: mit
Platform: any
Classifier: Development Status :: 4 - Beta
Classifier: Programming Language :: Python
Requires-Dist: bs4
Requires-Dist: requests
Provides-Extra: testing
Requires-Dist: pytest ; extra == 'testing'
Requires-Dist: pytest-cov ; extra == 'testing'
